[
  {
    "id": "work-laptop",
    "title": "Laptop Computer",
    "tags": [
      "computer",
      "laptop",
      "device",
      "work",
      "technology",
      "coding",
      "programming"
    ],
    "category": "work",
    "license": "CC0",
    "svg_path": "/illustrations/work/laptop.svg",
    "created_at": "2024-01-15T10:00:00Z",
    "dimensions": {
      "width": 512,
      "height": 512
    }
  },
  {
    "id": "work-meeting",
    "title": "Team Meeting",
    "tags": [
      "meeting",
      "team",
      "collaboration",
      "business",
      "discussion",
      "workspace"
    ],
    "category": "work",
    "license": "CC0",
    "svg_path": "/illustrations/work/meeting.svg",
    "created_at": "2024-01-16T14:30:00Z",
    "dimensions": {
      "width": 512,
      "height": 512
    }
  },
  {
    "id": "work-presentation",
    "title": "Business Presentation",
    "tags": [
      "presentation",
      "chart",
      "business",
      "analytics",
      "meeting",
      "graph"
    ],
    "category": "work",
    "license": "CC0",
    "svg_path": "/illustrations/work/presentation.svg",
    "created_at": "2024-01-17T09:15:00Z",
    "dimensions": {
      "width": 512,
      "height": 512
    }
  },
  {
    "id": "people-developer",
    "title": "Software Developer",
    "tags": [
      "developer",
      "coding",
      "person",
      "work",
      "programming",
      "computer",
      "software"
    ],
    "category": "people",
    "license": "CC0",
    "svg_path": "/illustrations/people/developer.svg",
    "created_at": "2024-01-18T11:20:00Z",
    "dimensions": {
      "width": 512,
      "height": 512
    }
  },
  {
    "id": "people-team",
    "title": "Team Collaboration",
    "tags": ["team", "collaboration", "people", "group", "work", "meeting"],
    "category": "people",
    "license": "CC0",
    "svg_path": "/illustrations/people/team.svg",
    "created_at": "2024-01-19T16:45:00Z",
    "dimensions": {
      "width": 512,
      "height": 512
    }
  },
  {
    "id": "objects-coffee",
    "title": "Coffee Cup",
    "tags": ["coffee", "drink", "work", "break", "cup", "beverage"],
    "category": "objects",
    "license": "CC0",
    "svg_path": "/illustrations/objects/coffee.svg",
    "created_at": "2024-01-20T08:30:00Z",
    "dimensions": {
      "width": 512,
      "height": 512
    }
  },
  {
    "id": "objects-plant",
    "title": "Office Plant",
    "tags": ["plant", "office", "decoration", "green", "workspace", "nature"],
    "category": "objects",
    "license": "CC0",
    "svg_path": "/illustrations/objects/plant.svg",
    "created_at": "2024-01-21T13:00:00Z",
    "dimensions": {
      "width": 512,
      "height": 512
    }
  },
  {
    "id": "technology-smartphone",
    "title": "Smartphone",
    "tags": [
      "smartphone",
      "mobile",
      "device",
      "technology",
      "communication",
      "app"
    ],
    "category": "technology",
    "license": "CC0",
    "svg_path": "/illustrations/technology/smartphone.svg",
    "created_at": "2024-01-22T10:15:00Z",
    "dimensions": {
      "width": 512,
      "height": 512
    }
  },
  {
    "id": "technology-cloud",
    "title": "Cloud Computing",
    "tags": [
      "cloud",
      "computing",
      "technology",
      "storage",
      "server",
      "internet"
    ],
    "category": "technology",
    "license": "CC0",
    "svg_path": "/illustrations/technology/cloud.svg",
    "created_at": "2024-01-23T15:30:00Z",
    "dimensions": {
      "width": 512,
      "height": 512
    }
  },
  {
    "id": "education-book",
    "title": "Study Book",
    "tags": ["book", "education", "learning", "study", "knowledge", "reading"],
    "category": "education",
    "license": "CC0",
    "svg_path": "/illustrations/education/book.svg",
    "created_at": "2024-01-24T12:00:00Z",
    "dimensions": {
      "width": 512,
      "height": 512
    }
  },
  {
    "id": "education-graduation",
    "title": "Graduation Cap",
    "tags": [
      "graduation",
      "education",
      "achievement",
      "degree",
      "university",
      "learning"
    ],
    "category": "education",
    "license": "CC0",
    "svg_path": "/illustrations/education/graduation.svg",
    "created_at": "2024-01-25T14:45:00Z",
    "dimensions": {
      "width": 512,
      "height": 512
    }
  },
  {
    "id": "nature-tree",
    "title": "Growing Tree",
    "tags": ["tree", "nature", "growth", "environment", "green", "plant"],
    "category": "nature",
    "license": "CC0",
    "svg_path": "/illustrations/nature/tree.svg",
    "created_at": "2024-01-26T09:30:00Z",
    "dimensions": {
      "width": 512,
      "height": 512
    }
  }
]
